{
	"block_style_id": "container-maxi-1443e495-u",
	"css_value": "body.maxi-blocks--active #container-maxi-1443e495-u{min-width:100%;box-shadow:0px 0px 0px 0px rgba(var(--maxi-light-color-8,150,176,203),1);padding-top:200px;padding-right:0px;padding-bottom:200px;padding-left:0px;flex-wrap:wrap;justify-content:flex-end;flex-direction:column;align-items:unset;align-content:unset;row-gap:20px;}body.maxi-blocks--active #container-maxi-1443e495-u > .maxi-background-displayer .maxi-background-displayer__1{width:100%;height:100%;background-color:rgba(var(--maxi-light-color-1,255,255,255),1);display:block;}body.maxi-blocks--active #container-maxi-1443e495-u > .maxi-background-displayer .maxi-background-displayer__2{background-image:url('_path_to_replace_404-page-ffp-pro-01/images/ffp-pro-1-1710328113-450755224-1710328113-1263429212.webp');background-size:cover;background-repeat:no-repeat;background-position:center top;background-origin:padding-box;background-clip:border-box;background-attachment:scroll;opacity:1;-webkit-transform:translate3d(0,0,0);width:100%;height:100%;bottom:200px;display:block;}@media only screen and (max-width:1366px){body.maxi-blocks--active #container-maxi-1443e495-u{padding-top:180px;padding-bottom:180px;}}@media only screen and (max-width:1024px){body.maxi-blocks--active #container-maxi-1443e495-u{padding-top:100px;padding-bottom:100px;}}@media only screen and (max-width:767px){body.maxi-blocks--active #container-maxi-1443e495-u{padding-top:80px;padding-bottom:80px;}}@media only screen and (max-width:480px){body.maxi-blocks--active #container-maxi-1443e495-u{padding-top:50px;padding-bottom:50px;}}",
	"fonts_value": "{\"Roboto\":{\"weight\":\"400,700\",\"style\":\"normal\"}}",
	"active_custom_data": "1",
	"custom_data_value": null
}
